exec_notifier.py
exec_notifier-0.1.33.dist-info/entry_points.txt
exec_notifier-0.1.33.dist-info/WHEEL
exec_notifier-0.1.33.dist-info/METADATA
exec_notifier-0.1.33.dist-info/RECORD
