Metadata-Version: 2.1
Name: exec-notifier
Version: 0.1.33
Summary: Tool to notify you when command will be executed.
Home-page: https://github.com/tikerlade/exec-notifier
Author: Ivan Kuznetsov
Author-email: tikerlade@gmail.com
Requires-Python: >=3.4,<4.0
Classifier: Programming Language :: Python :: 3
Classifier: Programming Language :: Python :: 3.4
Classifier: Programming Language :: Python :: 3.5
Classifier: Programming Language :: Python :: 3.6
Classifier: Programming Language :: Python :: 3.7
Classifier: Programming Language :: Python :: 3.8
Classifier: Programming Language :: Python :: 3.9
Requires-Dist: requests (>=2.25.1,<3.0.0)
Project-URL: Repository, https://github.com/tikerlade/exec-notifier
